decunicoder/__init__.py
decunicoder/unicoder.py
decunicoder-1.0.0.dist-info/METADATA
decunicoder-1.0.0.dist-info/WHEEL
decunicoder-1.0.0.dist-info/top_level.txt
decunicoder-1.0.0.dist-info/RECORD
