Metadata-Version: 2.1
Name: decunicoder
Version: 1.0.0
Summary: A Unicode encoding and decoding utility library
Author: SuperAssi2025
Keywords: unicode encoding decoding text-processing
Classifier: Development Status :: 5 - Production/Stable
Classifier: Intended Audience :: Developers
Classifier: License :: OSI Approved :: MIT License
Classifier: Programming Language :: Python :: 3
Classifier: Topic :: Text Processing :: General
Requires-Python: >=3.6
